ancombc_viz/__init__.py
ancombc_viz/main.py
ancombc_viz/plotting.py
ancombc_viz/utils.py
test/tests.py
ancombcviz-0.0.2.dist-info/METADATA
ancombcviz-0.0.2.dist-info/WHEEL
ancombcviz-0.0.2.dist-info/entry_points.txt
ancombcviz-0.0.2.dist-info/top_level.txt
ancombcviz-0.0.2.dist-info/RECORD
