Metadata-Version: 2.4
Name: ancombcviz
Version: 0.0.2
Author-email: Wooyeong Park <pss8993@jbnu.ac.kr>
Requires-Python: >=3.12
Requires-Dist: numpy>=2.0
Requires-Dist: pandas
Requires-Dist: matplotlib
Requires-Dist: seaborn
Requires-Dist: scikit-bio>=0.7.1
